myurls/__init__.py
myurls/urls.py
myurls-0.2.dist-info/METADATA
myurls-0.2.dist-info/WHEEL
myurls-0.2.dist-info/top_level.txt
myurls-0.2.dist-info/RECORD
