Metadata-Version: 2.1
Name: myurls
Version: 0.2
Summary: A simple package to store URLs for Netflix, Spotify, and Crunchyroll.
Home-page: https://github.com/dicky-alfansyah
Author: M Dicky Alfansyah
Author-email: dickyalfansyaah@gmail.com
License: MIT
Keywords: netflix,spotify,crunchyroll
Classifier: Development Status :: 3 - Alpha
Classifier: Intended Audience :: Developers
Classifier: License :: OSI Approved :: MIT License
Classifier: Programming Language :: Python :: 3
Classifier: Programming Language :: Python :: 3.6
Classifier: Programming Language :: Python :: 3.7
Classifier: Programming Language :: Python :: 3.8
Classifier: Programming Language :: Python :: 3.9
Classifier: Programming Language :: Python :: 3.10
Classifier: Programming Language :: Python :: 3.11
